mazgi_sandbox_4d36b809/__init__.py
mazgi_sandbox_4d36b809/__main__.py
mazgi_sandbox_4d36b809/main.py
mazgi_sandbox_4d36b809/one/__init__.py
mazgi_sandbox_4d36b809/one/one_class.py
mazgi_sandbox_4d36b809/two/__init__.py
mazgi_sandbox_4d36b809/two/two_class.py
mazgi_sandbox_4d36b809-0.0.1.dist-info/METADATA
mazgi_sandbox_4d36b809-0.0.1.dist-info/WHEEL
mazgi_sandbox_4d36b809-0.0.1.dist-info/entry_points.txt
mazgi_sandbox_4d36b809-0.0.1.dist-info/top_level.txt
mazgi_sandbox_4d36b809-0.0.1.dist-info/RECORD
