Metadata-Version: 2.1
Name: mazgi-sandbox-4d36b809
Version: 0.0.1
Summary: Example PKG
Home-page: https://github.com/mazgi-sandbox/201911.spike.python-pkg
Author: Hidenori MATSUKI
Author-email: dev@mazgi.com
License: UNKNOWN
Platform: UNKNOWN
Classifier: Programming Language :: Python :: 3
Classifier: License :: OSI Approved :: MIT License
Requires-Python: >=3.6
Requires-Dist: pyyaml
